mailbit/__init__.py
mailbit/mailbit.py
mailbit-0.1.6.dist-info/METADATA
mailbit-0.1.6.dist-info/WHEEL
mailbit-0.1.6.dist-info/top_level.txt
mailbit-0.1.6.dist-info/RECORD
